README.md
setup.py
financial_analysis/__init__.py
financial_analysis/returns.py
financial_analysis/set_freq.py
financial_analysis/volatility.py
financial_analysis.egg-info/PKG-INFO
financial_analysis.egg-info/SOURCES.txt
financial_analysis.egg-info/dependency_links.txt
financial_analysis.egg-info/not-zip-safe
financial_analysis.egg-info/requires.txt
financial_analysis.egg-info/top_level.txt