Metadata-Version: 2.1
Name: financial-analysis
Version: 1.1.3
Summary: A pandas extension for performing financial analysis on trade data.
Home-page: https://github.com/Kautenja/financial-analysis
Author: Christian Kauten
Author-email: kautencreations@gmail.com
License: MIT
Keywords: Finance Data Equity Option Future Index
Platform: UNKNOWN
Classifier: Development Status :: 4 - Beta
Classifier: Intended Audience :: Financial and Insurance Industry
Classifier: Intended Audience :: Science/Research
Classifier: License :: OSI Approved :: MIT License
Classifier: Operating System :: MacOS :: MacOS X
Classifier: Operating System :: POSIX :: Linux
Classifier: Operating System :: Microsoft :: Windows
Classifier: Programming Language :: Python :: 3 :: Only
Classifier: Programming Language :: Python :: 3.6
Classifier: Programming Language :: Python :: 3.7
Classifier: Topic :: Office/Business :: Financial
Classifier: Topic :: Office/Business :: Financial :: Investment
